{
  "Тест 1": {
    "scale": 50,
    "grid": 0.5,
    "wallThickness": 0.2,
    "nodes": [
      {
        "id": 1,
        "x": 626.6666870117188,
        "y": 469.3333740234375
      },
      {
        "id": 2,
        "x": 626.6666870117188,
        "y": 730.3407822195434
      },
      {
        "id": 3,
        "x": 897.3433673722589,
        "y": 730.3407822195434
      },
      {
        "id": 4,
        "x": 897.3433673722589,
        "y": 469.3325480589015
      }
    ],
    "walls": [
      {
        "id": 1,
        "name": "Стена 1",
        "a": 1,
        "b": 2,
        "thickness": 0.2
      },
      {
        "id": 2,
        "name": "Стена 2",
        "a": 2,
        "b": 3,
        "thickness": 0.2
      },
      {
        "id": 3,
        "name": "Стена 3",
        "a": 3,
        "b": 4,
        "thickness": 0.2
      },
      {
        "id": 4,
        "name": "Стена 4",
        "a": 4,
        "b": 1,
        "thickness": 0.2
      }
    ]
  }
}